requests_pkcs12.py
requests_pkcs12-1.26.dist-info/LICENSE
requests_pkcs12-1.26.dist-info/METADATA
requests_pkcs12-1.26.dist-info/WHEEL
requests_pkcs12-1.26.dist-info/top_level.txt
requests_pkcs12-1.26.dist-info/RECORD
