Metadata-Version: 2.1
Name: requests-pkcs12
Version: 1.26
Summary: Add PKCS#12 support to the requests library in a clean way, without monkey patching or temporary files
Home-page: https://github.com/m-click/requests_pkcs12
Author: Volker Diels-Grabsch
Author-email: volker.diels-grabsch@m-click.aero
License: ISC
Classifier: Development Status :: 5 - Production/Stable
Classifier: Intended Audience :: Developers
Classifier: License :: OSI Approved :: ISC License (ISCL)
Classifier: Programming Language :: Python :: 3
Classifier: Topic :: Software Development :: Libraries
Requires-Python: >=3.7
License-File: LICENSE
Requires-Dist: cryptography>=42.0.0
Requires-Dist: requests>=2.32.5
Provides-Extra: dev
Requires-Dist: twine>=3.4.2; extra == "dev"
Requires-Dist: wheel>=0.37.0; extra == "dev"
